mltrack/__init__.py
mltrack/__main__.py
mltrack/mltrack.py
mltrack/docs_assets/gen_figures.py
mltrack/docs_assets/sample
mltrack/docs_assets/sample.svg
mltrack/docs_assets/step_1
mltrack/docs_assets/step_1.svg
mltrack/docs_assets/step_2
mltrack/docs_assets/step_2.svg
mltrack/templates/build_features_py.j2
mltrack/templates/dot_env.j2
mltrack/templates/dot_gitignore.j2
mltrack/templates/dot_makefile.j2
mltrack/templates/download_data_py.j2
mltrack/templates/eval_model_py.j2
mltrack/templates/featurizer_py.j2
mltrack/templates/learn_features_py.j2
mltrack/templates/license_apache.j2
mltrack/templates/license_gpl.j2
mltrack/templates/license_mit.j2
mltrack/templates/make_dataset_py.j2
mltrack/templates/mlt_dependencies.j2
mltrack/templates/readme.j2
mltrack/templates/settings_py.j2
mltrack/templates/train_model_py.j2
mltrack-0.0.2.dist-info/LICENSE
mltrack-0.0.2.dist-info/METADATA
mltrack-0.0.2.dist-info/WHEEL
mltrack-0.0.2.dist-info/entry_points.txt
mltrack-0.0.2.dist-info/top_level.txt
mltrack-0.0.2.dist-info/RECORD
