Metadata-Version: 2.1
Name: mltrack
Version: 0.0.2
Summary: MLtrack: Track your ML workflow from the terminal
Home-page: UNKNOWN
Author: S.Shankar
Author-email: orthogonal.eigenvector@gmail.com
License: UNKNOWN
Platform: UNKNOWN
Requires-Python: >=3.6
Requires-Dist: jinja2
